{
    "登記案號": "098法登社000009",
    "類別": "2",
    "案由": "1",
    "主任": "詹駿鴻",
    "登記號數": "65",
    "收件日期": "0980806",
    "登記日期": "0980813",
    "公告日期": "0980814",
    "登記簿": "2冊29頁",
    "任期判定": "",
    "屆期判定": "",
    "法人代表": "理事長",
    "法人名稱": "社團法人苗栗縣承龍婚友協會",
    "設立登記日期": "0980813",
    "主事務所": "苗栗縣頭份鎮合興里2鄰中央路596號一樓",
    "目的": "本協會結合苗栗縣未婚男女聯誼共同為提倡經濟、文化、教育並提高縣民生活、知識品質。透過聯誼尋找理想伴侶，創造幸福美滿婚姻與家庭。並從事跨國境外婚姻謀合。",
    "捐助方法": "1、入會費。2、常年會費。3、事業費。4、會員捐款。5、委託收益。6、基金及孳息。7、其他收入。",
    "許可機關日期": "苗栗縣政府中華民國98年6月4日府勞社行字第0980091291號函",
    "存立時期": "永久",
    "財產總額": "20000",
    "結案原因": "1",
    "結案日期": "0980813",
    "歸檔日期": "0990203",
    "發證日期": "0980827",
    "送達代收人姓名": "",
    "送達代收人住址": "",
    "郵遞區號": "",
    "清算人": "",
    "變更原因": "",
    "註銷日期": "",
    "撤銷日期": "",
    "撤(註)銷機關文號": "",
    "撤(註)銷原因 ": "",
    "url": {
        "staff": "http:\/\/cdcb.judicial.gov.tw\/abbs\/wkw\/WHD6K04.jsp?bc=098&cd=%AAk%B5n%AA%C0&de=000009&ef=MLD&fg=1",
        "office": "http:\/\/cdcb.judicial.gov.tw\/abbs\/wkw\/WHD6K07.jsp?bc=098&cd=%AAk%B5n%AA%C0&de=000009&ef=MLD&fg=1"
    },
    "董監事": [],
    "分事務所": []
}