{
    "登記案號": "094法登他000363",
    "類別": "1",
    "案由": "2",
    "主任": "陳茂哲",
    "登記號數": "2090",
    "收件日期": "0940428",
    "登記日期": "0940503",
    "公告日期": "0940503",
    "登記簿": "81冊22頁",
    "任期判定": "1",
    "屆期判定": "3",
    "法人代表": "張秀蓮",
    "法人名稱": "財團法人汽車交通事故特別補償基金",
    "設立登記日期": "0870206",
    "主事務所": "台北市信義區信義路5段150巷2號18樓",
    "目的": "使汽車交通事故之受害人均能依本法規定獲得基本保障。",
    "捐助方法": "由保險業務發展基金管理委員會捐助",
    "許可機關日期": "財政部八十七年一月十三日　台財保第八六０八一七七三一號函",
    "存立時期": "永久",
    "財產總額": "3227308214",
    "結案原因": "1",
    "結案日期": "0940503",
    "歸檔日期": "0950927",
    "發證日期": "0940510",
    "送達代收人姓名": "",
    "送達代收人住址": "",
    "郵遞區號": "",
    "清算人": "",
    "變更原因": "董事長楊子江因職務異動卸任，補選繼任董事長及增置首屆監察人繼任董事長及新任監察人印鑑。\n原捐助章程第3條、第8條、第10條條文修正、增訂修正後第11條、第12條條文、原第11條、第12條調整條次為第13條、第14條、原第13條、第14條條文修正並調整條次為第15條、第16條、原第15條、第16條調整條次為第17條、第18條經本院94年度法字第1號民事裁定准予補充變更。",
    "註銷日期": "",
    "撤銷日期": "",
    "撤(註)銷機關文號": "",
    "撤(註)銷原因 ": "",
    "url": {
        "staff": "http:\/\/cdcb.judicial.gov.tw\/abbs\/wkw\/WHD6K04.jsp?bc=094&cd=%AAk%B5n%A5L&de=000363&ef=TPD&fg=1",
        "office": "http:\/\/cdcb.judicial.gov.tw\/abbs\/wkw\/WHD6K07.jsp?bc=094&cd=%AAk%B5n%A5L&de=000363&ef=TPD&fg=1"
    },
    "董監事": [
        [
            "董事長",
            "張秀蓮"
        ],
        [
            "董事",
            "魏寶生"
        ],
        [
            "董事",
            "劉宗榮"
        ],
        [
            "董事",
            "張邱春"
        ],
        [
            "董事",
            "李龍文"
        ],
        [
            "董事",
            "高福源"
        ],
        [
            "董事",
            "李宗嶽"
        ],
        [
            "董事",
            "石燦明"
        ],
        [
            "董事",
            "郭本厚"
        ],
        [
            "監察人",
            "凌?瘧_"
        ],
        [
            "監察人",
            "許文聖"
        ],
        [
            "監察人",
            "彭金隆"
        ]
    ],
    "分事務所": []
}