{
    "登記案號": "100法登他000566",
    "類別": "1",
    "案由": "2",
    "主任": "楊志純",
    "登記號數": "2661",
    "收件日期": "1000523",
    "登記日期": "1000524",
    "公告日期": "1000524",
    "登記簿": "106冊77頁",
    "任期判定": "2",
    "屆期判定": "3",
    "法人代表": "張黃美珠",
    "法人名稱": "財團法人臺北市松陽社會福利事業基金會",
    "設立登記日期": "0941114",
    "主事務所": "台北市萬華區峨眉街139號3樓",
    "目的": "本基金會以自行辦理、接受委辦或共同辦理等方式，連結政府暨民間的力量，積極倡導或推展有關青少年福利服務、休閒、教育、預防犯罪等活動，以營造青少年豐裕的文化環境，進而建立青少年的優質文化，並預防青少年犯罪為設置宗旨。",
    "捐助方法": "由張松先生、寶明建設股份有限公司、鴻暘建設股份有限公司、日鑫開發股份有限公司共同捐助",
    "許可機關日期": "臺北市政府社會局中華民國94年10月21日北市社六字第09440467400號函",
    "存立時期": "永久",
    "財產總額": "10000000",
    "結案原因": "1",
    "結案日期": "1000524",
    "歸檔日期": "",
    "發證日期": "1000601",
    "送達代收人姓名": "",
    "送達代收人住址": "",
    "郵遞區號": "",
    "清算人": "",
    "變更原因": "董事董事印鑑。\n原捐助章程第4條主事務所經董事會決議修正，報經主管機關同意備查。",
    "註銷日期": "",
    "撤銷日期": "",
    "撤(註)銷機關文號": "",
    "撤(註)銷原因 ": "",
    "url": {
        "staff": "http:\/\/cdcb.judicial.gov.tw\/abbs\/wkw\/WHD6K04.jsp?bc=094&cd=%AAk%B5n%A5L&de=000566&ef=TPD&fg=1",
        "office": "http:\/\/cdcb.judicial.gov.tw\/abbs\/wkw\/WHD6K07.jsp?bc=094&cd=%AAk%B5n%A5L&de=000566&ef=TPD&fg=1"
    },
    "董監事": [
        [
            "董事長",
            "謝長堯"
        ],
        [
            "董事",
            "蕭介生"
        ],
        [
            "董事",
            "李志文"
        ],
        [
            "董事",
            "曹興誠"
        ],
        [
            "董事",
            "何既明"
        ],
        [
            "董事",
            "李伯皇"
        ],
        [
            "董事",
            "李明濱"
        ],
        [
            "董事",
            "陳祈安"
        ],
        [
            "監察人",
            "王正一"
        ],
        [
            "董　事",
            "陳致遠"
        ]
    ],
    "分事務所": []
}