{
    "登記案號": "098法登他000016",
    "類別": "1",
    "案由": "2",
    "主任": "楊志純",
    "登記號數": "2357",
    "收件日期": "0980107",
    "登記日期": "0980108",
    "公告日期": "0980108",
    "登記簿": "91冊57頁",
    "任期判定": "2",
    "屆期判定": "6",
    "法人代表": "吳　渝",
    "法人名稱": "財團法人吳京文教基金會",
    "設立登記日期": "0870819",
    "主事務所": "台北市松山區光復南路67號12樓",
    "目的": "以致力公共事務研究，推動相關之學術文化活動，以服務社會為宗旨。",
    "捐助方法": "由冠瑋電子公司等六家公司共同捐助",
    "許可機關日期": "教育部中華民國八十七年八月十三日台社（四）字第八七０九一八０七號函",
    "存立時期": "永久",
    "財產總額": "30000000",
    "結案原因": "1",
    "結案日期": "0980108",
    "歸檔日期": "0981015",
    "發證日期": "0980116",
    "送達代收人姓名": "",
    "送達代收人住址": "",
    "郵遞區號": "",
    "清算人": "",
    "變更原因": "董事董事印鑑。",
    "註銷日期": "",
    "撤銷日期": "",
    "撤(註)銷機關文號": "",
    "撤(註)銷原因 ": "",
    "url": {
        "staff": "http:\/\/cdcb.judicial.gov.tw\/abbs\/wkw\/WHD6K04.jsp?bc=087&cd=%AAk%B5n%A5L&de=000016&ef=TPD&fg=1",
        "office": "http:\/\/cdcb.judicial.gov.tw\/abbs\/wkw\/WHD6K07.jsp?bc=087&cd=%AAk%B5n%A5L&de=000016&ef=TPD&fg=1"
    },
    "董監事": [
        [
            "董事長",
            "嚴　道"
        ],
        [
            "常務董事",
            "陳寬強"
        ],
        [
            "常務董事",
            "黃伯超"
        ],
        [
            "常務董事",
            "張仙平"
        ],
        [
            "常務董事",
            "穆閩珠"
        ],
        [
            "常務董事",
            "黃松元"
        ],
        [
            "常務董事",
            "賴東明"
        ],
        [
            "董事",
            "蕭正心"
        ],
        [
            "董事",
            "張美珥"
        ],
        [
            "董事",
            "許淵國"
        ],
        [
            "董事",
            "金小原"
        ],
        [
            "董事",
            "蔡世滋"
        ],
        [
            "董事",
            "陳嘉男"
        ],
        [
            "董事",
            "梁吳蓓琳"
        ],
        [
            "董事",
            "黃國彥"
        ]
    ],
    "分事務所": []
}