{
    "登記案號": "095法登社000044",
    "類別": "2",
    "案由": "1",
    "主任": "陳茂哲",
    "登記號數": "1290",
    "收件日期": "0950509",
    "登記日期": "0950517",
    "公告日期": "0950517",
    "登記簿": "55冊17頁",
    "任期判定": "",
    "屆期判定": "",
    "法人代表": "陳淑珠",
    "法人名稱": "社團法人台北市婦女會",
    "設立登記日期": "0950517",
    "主事務所": "台北市中正區杭州南路1段11巷6號",
    "目的": "本會以喚起婦女之民族意識，愛國情操，結合婦女之智慧與力量，促進婦女社會地位，工作權、經濟權、參政權之平等，謀求婦女福祉，創造美滿和諧家庭與安和樂利社會為宗旨。",
    "捐助方法": "入會費、常年會費、政府補助費、會員之捐助、社團及社會人士捐助、特別捐款、附屬事業之盈餘、基金孳息",
    "許可機關日期": "臺北市政府社會局中華民國95年4月12日北市社一字第09533799400號函",
    "存立時期": "永久",
    "財產總額": "300000",
    "結案原因": "1",
    "結案日期": "0950517",
    "歸檔日期": "0970710",
    "發證日期": "0950524",
    "送達代收人姓名": "",
    "送達代收人住址": "",
    "郵遞區號": "",
    "清算人": "",
    "變更原因": "",
    "註銷日期": "",
    "撤銷日期": "",
    "撤(註)銷機關文號": "",
    "撤(註)銷原因 ": "",
    "url": {
        "staff": "http:\/\/cdcb.judicial.gov.tw\/abbs\/wkw\/WHD6K04.jsp?bc=095&cd=%AAk%B5n%AA%C0&de=000044&ef=TPD&fg=1",
        "office": "http:\/\/cdcb.judicial.gov.tw\/abbs\/wkw\/WHD6K07.jsp?bc=095&cd=%AAk%B5n%AA%C0&de=000044&ef=TPD&fg=1"
    },
    "董監事": [],
    "分事務所": []
}