{
    "登記案號": "085法登他000681",
    "類別": "1",
    "案由": "理事長",
    "主任": "高李麗珍\n085法登他000681",
    "登記號數": "2",
    "收件日期": "常務理事",
    "登記日期": "郭耀東\n085法登他000681",
    "公告日期": "3",
    "登記簿": "常務理事",
    "任期判定": "黃正雄\n085法登他000681",
    "屆期判定": "4",
    "法人代表": "理  事",
    "法人名稱": "周謹明\n085法登他000681",
    "設立登記日期": "5",
    "主事務所": "理  事",
    "目的": "許得賜\n085法登他000681",
    "捐助方法": "6",
    "許可機關日期": "理  事",
    "存立時期": "施慧玲\n085法登他000681",
    "財產總額": "7",
    "結案原因": "理  事",
    "結案日期": "紀惠容\n085法登他000681",
    "歸檔日期": "8",
    "發證日期": "理  事",
    "送達代收人姓名": "松國賢\n085法登他000681",
    "送達代收人住址": "9",
    "郵遞區號": "理  事",
    "清算人": "陳潘淑媛\n085法登他000681",
    "變更原因": "10",
    "註銷日期": "常務監事",
    "撤銷日期": "陳貴德\n085法登他000681",
    "撤(註)銷機關文號": "11",
    "撤(註)銷原因 ": "監  事",
    "url": {
        "staff": "http:\/\/cdcb.judicial.gov.tw\/abbs\/wkw\/WHD6K04.jsp?bc=085&cd=%AAk%B5n%A5L&de=000681&ef=TPD&fg=1",
        "office": "http:\/\/cdcb.judicial.gov.tw\/abbs\/wkw\/WHD6K07.jsp?bc=085&cd=%AAk%B5n%A5L&de=000681&ef=TPD&fg=1"
    },
    "董監事": [],
    "分事務所": []
}