{
    "登記案號": "078登000257",
    "類別": "1",
    "案由": "2",
    "主任": "林貴美",
    "登記號數": "842",
    "收件日期": "0781003",
    "登記日期": "0781006",
    "公告日期": "0781006",
    "登記簿": "39冊19頁",
    "任期判定": "2",
    "屆期判定": "4",
    "法人代表": "各董事",
    "法人名稱": "財團法人欣然氣體燃料事業研究服務社",
    "設立登記日期": "0690221",
    "主事務所": "台北市松山區南京東路4段100號12樓",
    "目的": "促進氣體燃料及有關工業之發展。研究加強城鎮及家庭用氣體燃料使用之安全。氣體燃料供銷技術之研究與服務。配合政府能源政策及行政措施之宣導與研究服務。其他有關事業之興辦與服務。",
    "捐助方法": "行政院國軍退除役官兵輔導委員會所屬液化石油氣供應處等單位捐助",
    "許可機關日期": "經濟部中華民國69年2月7日經(69)工字第04317號函",
    "存立時期": "永久",
    "財產總額": "1606170",
    "結案原因": "1",
    "結案日期": "0781006",
    "歸檔日期": "0781020",
    "發證日期": "0781011",
    "送達代收人姓名": "",
    "送達代收人住址": "",
    "郵遞區號": "",
    "清算人": "",
    "變更原因": "董事、監察人董事、監察人任期：任期4年，連選得連任。\n修正捐助及組織章程第1、2、5、6、7、14、15、16條並經本院78年度法字第32號民事裁定准予修正。\n變更法人印鑑。",
    "註銷日期": "",
    "撤銷日期": "",
    "撤(註)銷機關文號": "",
    "撤(註)銷原因 ": "",
    "url": {
        "staff": "http:\/\/cdcb.judicial.gov.tw\/abbs\/wkw\/WHD6K04.jsp?bc=069&cd=%B5n&de=000257&ef=TPD&fg=1",
        "office": "http:\/\/cdcb.judicial.gov.tw\/abbs\/wkw\/WHD6K07.jsp?bc=069&cd=%B5n&de=000257&ef=TPD&fg=1"
    },
    "董監事": [],
    "分事務所": []
}