{
    "登記案號": "080登000256",
    "類別": "1",
    "案由": "2",
    "主任": "王聖惠",
    "登記號數": "858",
    "收件日期": "0800430",
    "登記日期": "0800902",
    "公告日期": "0800902",
    "登記簿": "39冊51頁",
    "任期判定": "2",
    "屆期判定": "4",
    "法人代表": "姜潘純華",
    "法人名稱": "財團法人台北市中華基督教浸信會信德堂",
    "設立登記日期": "0690519",
    "主事務所": "台北市大安區敦化南路1段362號6樓",
    "目的": "本教會係根據新舊二約聖經真理，以聯合信徒敬拜真神，遵守主道，培養靈命，宣傳福音，普救世人，直到主來；並辦理社會服務、教育、救濟等事業為宗旨。",
    "捐助方法": "美南浸信會捐贈",
    "許可機關日期": "臺北市政府民政局中華民國69年5月2日北市民三字第3528號函",
    "存立時期": "永久",
    "財產總額": "17160000",
    "結案原因": "1",
    "結案日期": "0800902",
    "歸檔日期": "0800911",
    "發證日期": "0800905",
    "送達代收人姓名": "",
    "送達代收人住址": "",
    "郵遞區號": "",
    "清算人": "",
    "變更原因": "董事董事印鑑。",
    "註銷日期": "",
    "撤銷日期": "",
    "撤(註)銷機關文號": "",
    "撤(註)銷原因 ": "",
    "url": {
        "staff": "http:\/\/cdcb.judicial.gov.tw\/abbs\/wkw\/WHD6K04.jsp?bc=069&cd=%B5n&de=000256&ef=TPD&fg=1",
        "office": "http:\/\/cdcb.judicial.gov.tw\/abbs\/wkw\/WHD6K07.jsp?bc=069&cd=%B5n&de=000256&ef=TPD&fg=1"
    },
    "董監事": [],
    "分事務所": []
}