{
    "登記案號": "101法登他000398",
    "類別": "2",
    "案由": "2",
    "主任": "楊志純",
    "登記號數": "1963",
    "收件日期": "1010416",
    "登記日期": "1010417",
    "公告日期": "1010417",
    "登記簿": "88冊73頁",
    "任期判定": "2",
    "屆期判定": "",
    "法人代表": "董煥新",
    "法人名稱": "社團法人台北市淡江大學校友會",
    "設立登記日期": "1000413",
    "主事務所": "台北市信義區忠孝東路4段563號8樓",
    "目的": "本會以聯繫校友感情，砥礪品德，互助合作，協助母校發展為宗旨。",
    "捐助方法": "入會費、常年會費、會員捐款、基金及孳息、其他收入",
    "許可機關日期": "臺北市政府社會局中華民國86年9月11日北市社一字第8624995500號函",
    "存立時期": "永久",
    "財產總額": "5557908",
    "結案原因": "1",
    "結案日期": "1010417",
    "歸檔日期": "",
    "發證日期": "1010425",
    "送達代收人姓名": "陳素美",
    "送達代收人住址": "台北市中山區撫順街35號3樓",
    "郵遞區號": "104",
    "清算人": "",
    "變更原因": "改選理、監事，理、監事印鑑。",
    "註銷日期": "",
    "撤銷日期": "",
    "撤(註)銷機關文號": "",
    "撤(註)銷原因 ": "",
    "url": {
        "staff": "http:\/\/cdcb.judicial.gov.tw\/abbs\/wkw\/WHD6K04.jsp?bc=100&cd=%AAk%B5n%A5L&de=000398&ef=TPD&fg=1",
        "office": "http:\/\/cdcb.judicial.gov.tw\/abbs\/wkw\/WHD6K07.jsp?bc=100&cd=%AAk%B5n%A5L&de=000398&ef=TPD&fg=1"
    },
    "董監事": [],
    "分事務所": []
}