{
    "登記案號": "048法登000032",
    "類別": "1",
    "案由": "1",
    "主任": "鄭忠仁",
    "登記號數": "32",
    "收件日期": "0480615",
    "登記日期": "0480615",
    "公告日期": "0480618",
    "登記簿": "3冊22頁",
    "任期判定": "",
    "屆期判定": "0",
    "法人代表": "董事長",
    "法人名稱": "財團法人中華基督教信義會苗栗教會",
    "設立登記日期": "0480615",
    "主事務所": "苗栗縣苗栗鎮中苗里建功街九號",
    "目的": "闡揚基督福音擴展教堂兼施慈善救濟事業",
    "捐助方法": "由信徒自由樂捐或由信義總會即西差會捐助之",
    "許可機關日期": "四十七年十一月二十八日苗栗縣政府",
    "存立時期": "無限期",
    "財產總額": "257632",
    "結案原因": "1",
    "結案日期": "0870220",
    "歸檔日期": "0921224",
    "發證日期": "",
    "送達代收人姓名": "",
    "送達代收人住址": "",
    "郵遞區號": "",
    "清算人": "",
    "變更原因": "",
    "註銷日期": "",
    "撤銷日期": "",
    "撤(註)銷機關文號": "",
    "撤(註)銷原因 ": "",
    "url": {
        "staff": "http:\/\/cdcb.judicial.gov.tw\/abbs\/wkw\/WHD6K04.jsp?bc=048&cd=%AAk%B5n&de=000032&ef=SCD&fg=1",
        "office": "http:\/\/cdcb.judicial.gov.tw\/abbs\/wkw\/WHD6K07.jsp?bc=048&cd=%AAk%B5n&de=000032&ef=SCD&fg=1"
    },
    "董監事": [
        [
            "董事長",
            "鍾競生"
        ],
        [
            "董事",
            "顏自超"
        ],
        [
            "董事",
            "陳啟雲"
        ],
        [
            "董事",
            "駱南河"
        ],
        [
            "董事",
            "胡漢三"
        ],
        [
            "董事",
            "徐新民"
        ],
        [
            "董事",
            "白謙德"
        ]
    ],
    "分事務所": []
}