{
    "登記案號": "106法登他000041",
    "類別": "2",
    "案由": "2",
    "主任": "呂權芳",
    "登記號數": "383",
    "收件日期": "1060609",
    "登記日期": "1060612",
    "公告日期": "1060614",
    "登記簿": "10冊19頁",
    "任期判定": "1",
    "屆期判定": "2",
    "法人代表": "陳慧如",
    "法人名稱": "社團法人雲林縣饗響文教協會",
    "設立登記日期": "1040205",
    "主事務所": "雲林縣西螺鎮延平路464號",
    "目的": "本會以推廣雲林在地自然飲食、友善環境觀念，建構藝術文化、人文美學之展演空間與交流平台，致力促進人與環境和諧共存之理念，提升在地人文藝術發展為宗旨。",
    "捐助方法": "會費收入、捐贈收入",
    "許可機關日期": "雲林縣政府101年10月2日府社救字第1015607721號函",
    "存立時期": "永久",
    "財產總額": "196000",
    "結案原因": "1",
    "結案日期": "1060612",
    "歸檔日期": "",
    "發證日期": "1060620",
    "送達代收人姓名": "",
    "送達代收人住址": "",
    "郵遞區號": "",
    "清算人": "",
    "變更原因": "第一屆理、監事任期屆滿，改選產生第二屆理、監事。\n原章程第三章第十七條及二十一條經第二屆第二次會員大會議決變更，報經主管機關106年3月20日府社救二字第1062609103號函准予備查。",
    "註銷日期": "",
    "撤銷日期": "",
    "撤(註)銷機關文號": "",
    "撤(註)銷原因 ": "",
    "url": {
        "staff": "http:\/\/cdcb.judicial.gov.tw\/abbs\/wkw\/WHD6K04.jsp?bc=106&cd=%AAk%B5n%A5L&de=000041&ef=ULD&fg=1",
        "office": "http:\/\/cdcb.judicial.gov.tw\/abbs\/wkw\/WHD6K07.jsp?bc=106&cd=%AAk%B5n%A5L&de=000041&ef=ULD&fg=1"
    },
    "董監事": [
        [
            "理事長",
            "陳慧如"
        ],
        [
            "理事",
            "管美惠"
        ],
        [
            "理事",
            "游熙明"
        ],
        [
            "候補理事",
            "江季翰"
        ],
        [
            "理事",
            "鄭清霞"
        ],
        [
            "理事",
            "張秋子"
        ],
        [
            "理事",
            "楊文榮"
        ],
        [
            "理事",
            "劉金賢"
        ],
        [
            "理事",
            "李秋燕"
        ],
        [
            "理事",
            "廖世煒"
        ],
        [
            "候補理事",
            "賴怡君"
        ],
        [
            "常務監事",
            "龔羿丞"
        ],
        [
            "監事",
            "吳雅雯"
        ],
        [
            "監事",
            "程麗茹"
        ]
    ],
    "分事務所": []
}