{
    "登記案號": "096法登他001008",
    "類別": "1",
    "案由": "2",
    "主任": "陳茂哲",
    "登記號數": "1283",
    "收件日期": "0961106",
    "登記日期": "0961226",
    "公告日期": "0961226",
    "登記簿": "54冊9頁",
    "任期判定": "1",
    "屆期判定": "7",
    "法人代表": "張文雄",
    "法人名稱": "財團法人景文科技大學",
    "設立登記日期": "0770503",
    "主事務所": "台北縣新店市安忠路99號",
    "目的": "遵照國家教育政策暨現行教育法令之規定，辦理景文科技大學並謀其健全發展。",
    "捐助方法": "由張萬利、張武義、張蔡月桂、張勤、賴欣欣等捐助",
    "許可機關日期": "教育部七十五年七月三十一日　台（七五）技字第三二八一一號函",
    "存立時期": "永久",
    "財產總額": "2996641734",
    "結案原因": "1",
    "結案日期": "0961226",
    "歸檔日期": "0970912",
    "發證日期": "0970102",
    "送達代收人姓名": "",
    "送達代收人住址": "",
    "郵遞區號": "",
    "清算人": "",
    "變更原因": "原捐助章程第1條至第3條、第6條、第7條及董事會組織章程第1條、第2條、第4條、第7條、第9條、第11條條文修正經本院96年度法字第161號民事裁定准予補充變更。\n法人印信及董事萬其超印鑑變更。",
    "註銷日期": "",
    "撤銷日期": "",
    "撤(註)銷機關文號": "",
    "撤(註)銷原因 ": "",
    "url": {
        "staff": "http:\/\/cdcb.judicial.gov.tw\/abbs\/wkw\/WHD6K04.jsp?bc=077&cd=%AAk%B5n%A5L&de=001008&ef=TPD&fg=1",
        "office": "http:\/\/cdcb.judicial.gov.tw\/abbs\/wkw\/WHD6K07.jsp?bc=077&cd=%AAk%B5n%A5L&de=001008&ef=TPD&fg=1"
    },
    "董監事": [],
    "分事務所": []
}