{
    "登記案號": "097法登他000043",
    "類別": "1",
    "案由": "2",
    "主任": "鍾秀媛",
    "登記號數": "229",
    "收件日期": "0970319",
    "登記日期": "0970319",
    "公告日期": "0970320",
    "登記簿": "10冊3頁",
    "任期判定": "2",
    "屆期判定": "17",
    "法人代表": "張仁祥",
    "法人名稱": "財團法人新竹市立朝山國民小學教育發展基金會",
    "設立登記日期": "0810430",
    "主事務所": "新竹市中華路五段六四八巷一二六號",
    "目的": "一、協助政府推展教育建設。二、舉辦全校性校內外之各項教育活動。",
    "捐助方法": "地方熱心教育人士及校友自由捐助。",
    "許可機關日期": "八十一年二月十六日新竹市政府",
    "存立時期": "永久",
    "財產總額": "2136770",
    "結案原因": "1",
    "結案日期": "0970319",
    "歸檔日期": "0970606",
    "發證日期": "",
    "送達代收人姓名": "",
    "送達代收人住址": "",
    "郵遞區號": "",
    "清算人": "",
    "變更原因": "組織章程變更如下：第一條、第三條、第五條、第七條、第八條、第九條、第十條、第十一條、第十二條、第十三條、第十五條、第十七條、第十八條、第二十條、第二十一條、第二十二條部分修訂。第十四條完全刪除。",
    "註銷日期": "",
    "撤銷日期": "",
    "撤(註)銷機關文號": "",
    "撤(註)銷原因 ": "",
    "url": {
        "staff": "http:\/\/cdcb.judicial.gov.tw\/abbs\/wkw\/WHD6K04.jsp?bc=097&cd=%AAk%B5n%A5L&de=000043&ef=SCD&fg=1",
        "office": "http:\/\/cdcb.judicial.gov.tw\/abbs\/wkw\/WHD6K07.jsp?bc=097&cd=%AAk%B5n%A5L&de=000043&ef=SCD&fg=1"
    },
    "董監事": [
        [
            "董事長",
            "張仁祥"
        ],
        [
            "董事",
            "許德財"
        ],
        [
            "董事",
            "王順松"
        ],
        [
            "董事",
            "陳錦輝"
        ],
        [
            "董事",
            "林永標"
        ],
        [
            "董事",
            "陳聖賢"
        ],
        [
            "董事",
            "林文欽"
        ],
        [
            "董事",
            "陳智龍"
        ],
        [
            "董事",
            "陳敏富"
        ]
    ],
    "分事務所": []
}