{
    "登記案號": "093法登他000049",
    "類別": "1",
    "案由": "2",
    "主任": "謝怜聰",
    "登記號數": "370",
    "收件日期": "0930520",
    "登記日期": "0930520",
    "公告日期": "0930521",
    "登記簿": "12冊44頁",
    "任期判定": "2",
    "屆期判定": "3",
    "法人代表": "曾繁城",
    "法人名稱": "財團法人台積電文教基金會",
    "設立登記日期": "0870525",
    "主事務所": "新竹科學工業園區新竹市力行六路八號",
    "目的": "以贊助各項獎學金、講座、文藝活動、提昇人文精神為宗旨。",
    "捐助方法": "由台灣積體電路製造股份有限公司捐助",
    "許可機關日期": "教育部87.04.20台社四字第八七０三九四五三號",
    "存立時期": "永久",
    "財產總額": "319738360",
    "結案原因": "1",
    "結案日期": "0930520",
    "歸檔日期": "0930716",
    "發證日期": "",
    "送達代收人姓名": "",
    "送達代收人住址": "",
    "郵遞區號": "",
    "清算人": "",
    "變更原因": "",
    "註銷日期": "",
    "撤銷日期": "",
    "撤(註)銷機關文號": "",
    "撤(註)銷原因 ": "",
    "url": {
        "staff": "http:\/\/cdcb.judicial.gov.tw\/abbs\/wkw\/WHD6K04.jsp?bc=093&cd=%AAk%B5n%A5L&de=000049&ef=SCD&fg=1",
        "office": "http:\/\/cdcb.judicial.gov.tw\/abbs\/wkw\/WHD6K07.jsp?bc=093&cd=%AAk%B5n%A5L&de=000049&ef=SCD&fg=1"
    },
    "董監事": [
        [
            "董事長",
            "曾繁城"
        ],
        [
            "董事",
            "陳國慈"
        ],
        [
            "董事",
            "邢智田"
        ],
        [
            "董事",
            "蔡能賢"
        ],
        [
            "董事",
            "張淑芬"
        ],
        [
            "董事",
            "張秉衡"
        ],
        [
            "董事",
            "張銘江"
        ]
    ],
    "分事務所": []
}