{
    "登記案號": "088法登他000334",
    "類別": "2",
    "案由": "2",
    "主任": "許立民",
    "登記號數": "541",
    "收件日期": "0880504",
    "登記日期": "0880504",
    "公告日期": "0880504",
    "登記簿": "19冊31頁",
    "任期判定": "1",
    "屆期判定": "3",
    "法人代表": "劉  芬",
    "法人名稱": "社團法人台北市心理復健家屬聯合協會",
    "設立登記日期": "0860429",
    "主事務所": "台北市羅斯福路三段一二五號三樓之一",
    "目的": "以促進精神病患之家屬相互協助，交換醫療復健資訊，協助精神病患者就醫，及出院後做回歸社會之復健工作，並為其爭取應有之權利與福利為宗旨。",
    "捐助方法": "社員繳納會費、委託收益及其他捐款。",
    "許可機關日期": "台北市政府社會局八十三年四月十三日　北市社一字第一六九一八號函同意設立",
    "存立時期": "永久",
    "財產總額": "448303",
    "結案原因": "1",
    "結案日期": "0880504",
    "歸檔日期": "0880513",
    "發證日期": "0880513",
    "送達代收人姓名": "",
    "送達代收人住址": "",
    "郵遞區號": "",
    "清算人": "",
    "變更原因": "理事長李有展、常務理事謝素娥、常務監事陳初鶯辭任理事及監事，選舉繼任理事長、常務理事、常務監事及遞補繼任理、監事，其繼任理事長、常務理事、常務監事、理事、監事印鑑。",
    "註銷日期": "",
    "撤銷日期": "",
    "撤(註)銷機關文號": "",
    "撤(註)銷原因 ": "",
    "url": {
        "staff": "http:\/\/cdcb.judicial.gov.tw\/abbs\/wkw\/WHD6K04.jsp?bc=086&cd=%AAk%B5n%A5L&de=000334&ef=TPD&fg=1",
        "office": "http:\/\/cdcb.judicial.gov.tw\/abbs\/wkw\/WHD6K07.jsp?bc=086&cd=%AAk%B5n%A5L&de=000334&ef=TPD&fg=1"
    },
    "董監事": [
        [
            "董事長",
            "劉富榮"
        ],
        [
            "董事",
            "林明河"
        ],
        [
            "董事",
            "王奕龍"
        ],
        [
            "董事",
            "王順正"
        ],
        [
            "董事",
            "田炳耀"
        ],
        [
            "董事",
            "冷章華"
        ],
        [
            "董事",
            "鄭文政"
        ],
        [
            "董事",
            "陳憲?N"
        ],
        [
            "董事",
            "尤家國"
        ],
        [
            "董事",
            "林韻笙"
        ],
        [
            "董事",
            "蔡兩全"
        ],
        [
            "董事",
            "莊文村"
        ],
        [
            "董事",
            "何重謀"
        ],
        [
            "董事",
            "陳進生"
        ],
        [
            "董事",
            "翁金發"
        ],
        [
            "董事",
            "廖進興"
        ],
        [
            "董事",
            "詹一新"
        ],
        [
            "董事",
            "蔡振華"
        ],
        [
            "董事",
            "蔡加寶"
        ],
        [
            "董事",
            "王元海"
        ],
        [
            "董事",
            "蕭鏡琦"
        ]
    ],
    "分事務所": []
}