{
    "登記案號": "090法登社000052",
    "類別": "9",
    "案由": "理  事",
    "主任": "林聰賢\n090法登社000052",
    "登記號數": "10",
    "收件日期": "理  事",
    "登記日期": "柯文進\n090法登社000052",
    "公告日期": "11",
    "登記簿": "理  事",
    "任期判定": "謝正義\n090法登社000052",
    "屆期判定": "12",
    "法人代表": "理  事",
    "法人名稱": "張有道\n090法登社000052",
    "設立登記日期": "13",
    "主事務所": "理  事",
    "目的": "賴豐喜\n090法登社000052",
    "捐助方法": "14",
    "許可機關日期": "理  事",
    "存立時期": "廖崇榮\n090法登社000052",
    "財產總額": "15",
    "結案原因": "常務監事",
    "結案日期": "陳耀勳\n090法登社000052",
    "歸檔日期": "16",
    "發證日期": "監  事",
    "送達代收人姓名": "林利吉\n090法登社000052",
    "送達代收人住址": "17",
    "郵遞區號": "監  事",
    "清算人": "張景雄\n090法登社000052",
    "變更原因": "18",
    "註銷日期": "監  事",
    "撤銷日期": "程清平\n090法登社000052",
    "撤(註)銷機關文號": "19",
    "撤(註)銷原因 ": "監  事",
    "url": {
        "staff": "http:\/\/cdcb.judicial.gov.tw\/abbs\/wkw\/WHD6K04.jsp?bc=090&cd=%AAk%B5n%AA%C0&de=000052&ef=TPD&fg=1",
        "office": "http:\/\/cdcb.judicial.gov.tw\/abbs\/wkw\/WHD6K07.jsp?bc=090&cd=%AAk%B5n%AA%C0&de=000052&ef=TPD&fg=1"
    },
    "董監事": [],
    "分事務所": []
}