{
    "登記案號": "095法登他000002",
    "類別": "2",
    "案由": "2",
    "主任": "陳茂哲",
    "登記號數": "355",
    "收件日期": "0950102",
    "登記日期": "0950113",
    "公告日期": "0950113",
    "登記簿": "13冊10頁",
    "任期判定": "1",
    "屆期判定": "11",
    "法人代表": "呂秀蓮",
    "法人名稱": "社團法人民主進步黨",
    "設立登記日期": "0820927",
    "主事務所": "台北市中正區北平東路30號8至10樓",
    "目的": "以實現本黨之綱領為目的。",
    "捐助方法": "黨費、捐款與其他收入",
    "許可機關日期": "內政部七十八年五月五日  台（七八）內民字第七０一八九六號函同意備案",
    "存立時期": "永久",
    "財產總額": "10000000",
    "結案原因": "1",
    "結案日期": "0950113",
    "歸檔日期": "0960206",
    "發證日期": "0950120",
    "送達代收人姓名": "",
    "送達代收人住址": "",
    "郵遞區號": "",
    "清算人": "",
    "變更原因": "中央常務執行委員柯建銘卸任立法院黨團總召集人，其職務改由趙永清繼任，住所如下：第11屆主席蘇貞昌辭任，其職務由中央常務執行員呂秀蓮代理。\n第11屆中央常務執行委員游錫坔、翁金珠辭任；林宗男因退黨喪失資格。\n繼任中央常務執行委員趙永清印鑑。",
    "註銷日期": "",
    "撤銷日期": "",
    "撤(註)銷機關文號": "",
    "撤(註)銷原因 ": "",
    "url": {
        "staff": "http:\/\/cdcb.judicial.gov.tw\/abbs\/wkw\/WHD6K04.jsp?bc=082&cd=%AAk%B5n%A5L&de=000002&ef=TPD&fg=1",
        "office": "http:\/\/cdcb.judicial.gov.tw\/abbs\/wkw\/WHD6K07.jsp?bc=082&cd=%AAk%B5n%A5L&de=000002&ef=TPD&fg=1"
    },
    "董監事": [],
    "分事務所": []
}