{
    "登記案號": "107法登社000048",
    "類別": "2",
    "案由": "1",
    "主任": "陳錦鑾",
    "登記號數": "1868",
    "收件日期": "1071206",
    "登記日期": "1071206",
    "公告日期": "1071206",
    "登記簿": "39冊26頁",
    "任期判定": "",
    "屆期判定": "",
    "法人代表": "理事長",
    "法人名稱": "社團法人台灣敬舜功德會",
    "設立登記日期": "1071206",
    "主事務所": "高雄市苓雅區大順三路183之3號1樓",
    "目的": "以慈善為宗旨，結合民間善心人士及團體機構的力量，配合政府的政策，並對社會清寒、貧苦、埋葬及家庭急難者，給予適當之救助，發揮人溺己溺，人肌己飢之精神，改善社會風氣，讓社會更祥和，推展社會慈善工作。",
    "捐助方法": "會費及捐助等",
    "許可機關日期": "內政部107年9月21日台內團字第1070063200號函　　　　",
    "存立時期": "永久",
    "財產總額": "25000",
    "結案原因": "1",
    "結案日期": "1071207",
    "歸檔日期": "",
    "發證日期": "",
    "送達代收人姓名": "",
    "送達代收人住址": "",
    "郵遞區號": "",
    "清算人": "",
    "變更原因": "",
    "註銷日期": "",
    "撤銷日期": "",
    "撤(註)銷機關文號": "",
    "撤(註)銷原因 ": "",
    "url": {
        "staff": "http:\/\/cdcb.judicial.gov.tw\/abbs\/wkw\/WHD6K04.jsp?bc=107&cd=%AAk%B5n%AA%C0&de=000048&ef=KSD&fg=1",
        "office": "http:\/\/cdcb.judicial.gov.tw\/abbs\/wkw\/WHD6K07.jsp?bc=107&cd=%AAk%B5n%AA%C0&de=000048&ef=KSD&fg=1"
    },
    "董監事": [
        [
            "理事長",
            "薛釗士"
        ],
        [
            "常務理事",
            "黃紫頌"
        ],
        [
            "常務理事",
            "溫金文"
        ],
        [
            "理事",
            "陳招榮"
        ],
        [
            "理事",
            "林武澐"
        ],
        [
            "理事",
            "吳慶杉"
        ],
        [
            "理事",
            "林麗雲"
        ],
        [
            "理事",
            "洪榮生"
        ],
        [
            "理事",
            "吳茂雄"
        ],
        [
            "常務監事",
            "李建興"
        ],
        [
            "監事",
            "薛澤鑫"
        ],
        [
            "監事",
            "張媄媮"
        ],
        [
            "",
            "任期3年"
        ]
    ],
    "分事務所": []
}