{
    "登記案號": "058登000015",
    "類別": "1",
    "案由": "2",
    "主任": "張秀芬",
    "登記號數": "82",
    "收件日期": "0580405",
    "登記日期": "0580411",
    "公告日期": "0580411",
    "登記簿": "6冊19頁",
    "任期判定": "2",
    "屆期判定": "",
    "法人代表": "林忠義",
    "法人名稱": "財團法人台北市林東山堂　",
    "設立登記日期": "0480429",
    "主事務所": "台北市建國北路143號",
    "目的": "本堂以宣揚儒道釋三教之道德及闡揚祖德、敦睦宗誼增進族人福利樹立團結互助精神並興辦慈善育英公益事業為宗旨。",
    "捐助方法": "由堂友捐助",
    "許可機關日期": "臺灣省臺北市政府中華民國48年4月14日(48)北市社組字第10788號通知",
    "存立時期": "永久",
    "財產總額": "60000",
    "結案原因": "1",
    "結案日期": "0580411",
    "歸檔日期": "0580711",
    "發證日期": "",
    "送達代收人姓名": "",
    "送達代收人住址": "",
    "郵遞區號": "",
    "清算人": "",
    "變更原因": "董、監事本堂惟因配合本市改升為院轄市經於57年8月18日舉開57年度第1次臨時堂友大會議決修正法人名稱捐助章程及改選董事林忠義等11名，並奉主管官署臺北市政府民政局58.3.3北市民二字第1620號通知准予核備在案。\n名稱：財團法人台北市林東山堂。\n印鑑：闊5.0公分長7.5公分長方形圖記及2.0公分四方形董事長職印圖記。\n修正組織暨捐助章程第1條至第19條（詳章程）。",
    "註銷日期": "",
    "撤銷日期": "",
    "撤(註)銷機關文號": "",
    "撤(註)銷原因 ": "",
    "url": {
        "staff": "http:\/\/cdcb.judicial.gov.tw\/abbs\/wkw\/WHD6K04.jsp?bc=048&cd=%B5n&de=000015&ef=TPD&fg=1",
        "office": "http:\/\/cdcb.judicial.gov.tw\/abbs\/wkw\/WHD6K07.jsp?bc=048&cd=%B5n&de=000015&ef=TPD&fg=1"
    },
    "董監事": [
        [
            "董事長",
            "陳蘭皋"
        ],
        [
            "董　事",
            "李連春"
        ],
        [
            "董　事",
            "張慕林"
        ],
        [
            "董　事",
            "薛繼壎"
        ],
        [
            "董　事",
            "沈覲泰"
        ]
    ],
    "分事務所": []
}