{
    "登記案號": "103法登他000275",
    "類別": "2",
    "案由": "2",
    "主任": "陳錦鑾",
    "登記號數": "1334",
    "收件日期": "1030807",
    "登記日期": "1030807",
    "公告日期": "1030808",
    "登記簿": "26冊13頁",
    "任期判定": "2",
    "屆期判定": "6",
    "法人代表": "理事長",
    "法人名稱": "社團法人高雄市多元家庭關愛協會",
    "設立登記日期": "1010201",
    "主事務所": "高雄市路竹區中正路9號",
    "目的": "本會以鼓勵多元家庭發展、促進權益，建立幸福家庭與和諧社會為宗旨。",
    "捐助方法": "會費及捐助",
    "許可機關日期": "高雄縣政府86年5月12日八六府社行字第084485號函",
    "存立時期": "永久",
    "財產總額": "100000",
    "結案原因": "1",
    "結案日期": "1030807",
    "歸檔日期": "1030910",
    "發證日期": "1030815",
    "送達代收人姓名": "",
    "送達代收人住址": "",
    "郵遞區號": "",
    "清算人": "",
    "變更原因": "法人圖記、理監事變更登記一、法人圖記變更。二、理監事變更：第5屆理監事任期屆滿，改選第6屆理監事。三理監事印鑑登記。",
    "註銷日期": "",
    "撤銷日期": "107年7月26日雄院和登1334字第1071014410號函移轉橋頭地方法院管轄",
    "撤(註)銷機關文號": "",
    "撤(註)銷原因 ": "",
    "url": {
        "staff": "http:\/\/cdcb.judicial.gov.tw\/abbs\/wkw\/WHD6K04.jsp?bc=103&cd=%AAk%B5n%A5L&de=000275&ef=KSD&fg=1",
        "office": "http:\/\/cdcb.judicial.gov.tw\/abbs\/wkw\/WHD6K07.jsp?bc=103&cd=%AAk%B5n%A5L&de=000275&ef=KSD&fg=1"
    },
    "董監事": [
        [
            "理事長",
            "陸錦慧"
        ],
        [
            "常務理事",
            "謝麗娟"
        ],
        [
            "常務理事",
            "陳淑敏"
        ],
        [
            "理事",
            "王儷潓"
        ],
        [
            "理事",
            "林孟潔"
        ],
        [
            "理事",
            "郭慧菁"
        ],
        [
            "理事",
            "趙秀卿"
        ],
        [
            "理事",
            "鄧秋蘭"
        ],
        [
            "理事",
            "郭玲枝"
        ],
        [
            "常務監事",
            "蔡家蓁"
        ],
        [
            "監事",
            "陳美惠"
        ],
        [
            "監事",
            "溫秀梅"
        ]
    ],
    "分事務所": []
}