{
    "登記案號": "086法登他000059",
    "類別": "1",
    "案由": "2",
    "主任": "張茂寅",
    "登記號數": "340",
    "收件日期": "0860203",
    "登記日期": "0860227",
    "公告日期": "0860227",
    "登記簿": "22冊27頁",
    "任期判定": "2",
    "屆期判定": "2",
    "法人代表": "顏武勝",
    "法人名稱": "財團法人台北市顏榮公忠信會",
    "設立登記日期": "0571205",
    "主事務所": "台北市新東街卅七號",
    "目的": "以宣揚實踐孝道，祭祀祖先，敦親睦族，輔助宗親福利為目的。",
    "捐助方法": "祭祀公業顏榮公所捐助",
    "許可機關日期": "台北市政府五十七年十一月六日　府新二字第四八二六０號函",
    "存立時期": "永久",
    "財產總額": "12976360",
    "結案原因": "1",
    "結案日期": "0860227",
    "歸檔日期": "0860530",
    "發證日期": "0860530",
    "送達代收人姓名": "",
    "送達代收人住址": "",
    "郵遞區號": "",
    "清算人": "",
    "變更原因": "董、監事代表法人之董事：顏武勝。\n董、監事印鑑。\n原捐助暨組織規章名稱及第三、四、十、十三、十六條經本院八十五年度\n法字第八五號民事裁定准予變更。",
    "註銷日期": "",
    "撤銷日期": "",
    "撤(註)銷機關文號": "",
    "撤(註)銷原因 ": "",
    "url": {
        "staff": "http:\/\/cdcb.judicial.gov.tw\/abbs\/wkw\/WHD6K04.jsp?bc=057&cd=%AAk%B5n%A5L&de=000059&ef=TPD&fg=1",
        "office": "http:\/\/cdcb.judicial.gov.tw\/abbs\/wkw\/WHD6K07.jsp?bc=057&cd=%AAk%B5n%A5L&de=000059&ef=TPD&fg=1"
    },
    "董監事": [],
    "分事務所": []
}