{
    "登記案號": "081登000358",
    "類別": "1",
    "案由": "1",
    "主任": "張茂寅",
    "登記號數": "1680",
    "收件日期": "0810930",
    "登記日期": "0811006",
    "公告日期": "0811006",
    "登記簿": "67冊31頁",
    "任期判定": "",
    "屆期判定": "",
    "法人代表": "尹麗珍",
    "法人名稱": "財團法人台北市私立大安老人養護所",
    "設立登記日期": "0811006",
    "主事務所": "台北市大安區安居街46巷5號1、3樓及7號1樓",
    "目的": "以提供罹患慢性疾病或癱瘓老人寧靜、安全、衛生之環境及設備，增進老人健康及確保老人生活照顧為目的。",
    "捐助方法": "由尹麗珍女士及曹宜中先生共同捐助",
    "許可機關日期": "臺北市政府社會局中華民國81年9月17日北市社四字第38794號函",
    "存立時期": "永久",
    "財產總額": "3480000",
    "結案原因": "1",
    "結案日期": "0811006",
    "歸檔日期": "0811231",
    "發證日期": "0811016",
    "送達代收人姓名": "",
    "送達代收人住址": "",
    "郵遞區號": "",
    "清算人": "",
    "變更原因": "",
    "註銷日期": "",
    "撤銷日期": "",
    "撤(註)銷機關文號": "",
    "撤(註)銷原因 ": "",
    "url": {
        "staff": "http:\/\/cdcb.judicial.gov.tw\/abbs\/wkw\/WHD6K04.jsp?bc=081&cd=%B5n&de=000358&ef=TPD&fg=1",
        "office": "http:\/\/cdcb.judicial.gov.tw\/abbs\/wkw\/WHD6K07.jsp?bc=081&cd=%B5n&de=000358&ef=TPD&fg=1"
    },
    "董監事": [
        [
            "董事長",
            "尹麗珍"
        ],
        [
            "董　事",
            "曹宜中"
        ],
        [
            "董　事",
            "楊台明"
        ],
        [
            "董　事",
            "黃秀葉"
        ],
        [
            "董　事",
            "張文炫"
        ],
        [
            "董　事",
            "林李梅英"
        ],
        [
            "董　事",
            "林明信"
        ]
    ],
    "分事務所": []
}