{
    "登記案號": "092法登他000034",
    "類別": "2",
    "案由": "2",
    "主任": "郭千黛",
    "登記號數": "24",
    "收件日期": "0920917",
    "登記日期": "0920917",
    "公告日期": "0920921",
    "登記簿": "1冊47頁",
    "任期判定": "2",
    "屆期判定": "2",
    "法人代表": "葉蒼斌",
    "法人名稱": "社團法人台灣省氣功養生協會",
    "設立登記日期": "0911021",
    "主事務所": "苗栗縣公館鄉五谷村四鄰一三二之一號",
    "目的": "以推廣養生氣功，移風易俗，端正社會風氣，促進全民健康，增進社會福利，進而興辦公益事業為宗旨。",
    "捐助方法": "會員會費，捐款，補助費或其他收入。",
    "許可機關日期": "臺灣省政府八九年五月二五日八九府社行字第二二四○五號函",
    "存立時期": "永久",
    "財產總額": "72860",
    "結案原因": "1",
    "結案日期": "0920922",
    "歸檔日期": "0930113",
    "發證日期": "",
    "送達代收人姓名": "",
    "送達代收人住址": "",
    "郵遞區號": "",
    "清算人": "",
    "變更原因": "",
    "註銷日期": "",
    "撤銷日期": "",
    "撤(註)銷機關文號": "",
    "撤(註)銷原因 ": "",
    "url": {
        "staff": "http:\/\/cdcb.judicial.gov.tw\/abbs\/wkw\/WHD6K04.jsp?bc=092&cd=%AAk%B5n%A5L&de=000034&ef=MLD&fg=1",
        "office": "http:\/\/cdcb.judicial.gov.tw\/abbs\/wkw\/WHD6K07.jsp?bc=092&cd=%AAk%B5n%A5L&de=000034&ef=MLD&fg=1"
    },
    "董監事": [
        [
            "理事長",
            "葉蒼斌"
        ],
        [
            "副理事長",
            "許延誌"
        ],
        [
            "常務理事",
            "吳德成"
        ],
        [
            "理事",
            "江宗源"
        ],
        [
            "理事",
            "白芳銘"
        ],
        [
            "理事",
            "黃教忠"
        ],
        [
            "理事",
            "莊毓震"
        ],
        [
            "理事",
            "莊志鏗"
        ],
        [
            "理事",
            "洪居清"
        ],
        [
            "常務監事",
            "張淨琇"
        ],
        [
            "監事",
            "黃秀蘭"
        ],
        [
            "監事",
            "蘇文娟"
        ]
    ],
    "分事務所": []
}