{
    "登記案號": "093法登他000045",
    "類別": "2",
    "案由": "2",
    "主任": "陳茂哲",
    "登記號數": "997",
    "收件日期": "0930116",
    "登記日期": "0930119",
    "公告日期": "0930119",
    "登記簿": "40冊29頁",
    "任期判定": "1",
    "屆期判定": "",
    "法人代表": "陳隆志",
    "法人名稱": "社團法人台灣國際法學會",
    "設立登記日期": "0920819",
    "主事務所": "台北市中山區南京東路二段一二五號九樓之一（九一Ｏ會議室）　　",
    "目的": "舉行演講、學術研究及其他相關學術活動。蒐集及交換國內外資料，以供參考。接受公私機構之委託研究並解答問題。刊行會誌、會報及相關之各類書刊。辦理與國內外有關機構與學術團體之學術聯繫、交流活動。推動國際法專門教學與研究機構之設立。其他促進國際法發展之相關活動。",
    "捐助方法": "入會費、常年會費、事業費、會員捐款、委託收益、基金及其孳息、其他收入",
    "許可機關日期": "內政部中華民國九十二年六月九日台內社字第０九二００二二一二０號函",
    "存立時期": "永久",
    "財產總額": "4000",
    "結案原因": "1",
    "結案日期": "0930119",
    "歸檔日期": "0931005",
    "發證日期": "0930203",
    "送達代收人姓名": "",
    "送達代收人住址": "",
    "郵遞區號": "",
    "清算人": "",
    "變更原因": "章程第一條、第三十條經會員大會決議修改，報經主管機關核備變更。",
    "註銷日期": "",
    "撤銷日期": "",
    "撤(註)銷機關文號": "",
    "撤(註)銷原因 ": "",
    "url": {
        "staff": "http:\/\/cdcb.judicial.gov.tw\/abbs\/wkw\/WHD6K04.jsp?bc=092&cd=%AAk%B5n%A5L&de=000045&ef=TPD&fg=1",
        "office": "http:\/\/cdcb.judicial.gov.tw\/abbs\/wkw\/WHD6K07.jsp?bc=092&cd=%AAk%B5n%A5L&de=000045&ef=TPD&fg=1"
    },
    "董監事": [],
    "分事務所": []
}