{
    "登記案號": "103法登他000003",
    "類別": "2",
    "案由": "2",
    "主任": "吳玉金",
    "登記號數": "51",
    "收件日期": "1030221",
    "登記日期": "1030221",
    "公告日期": "1020224",
    "登記簿": "2冊1頁",
    "任期判定": "1",
    "屆期判定": "3",
    "法人代表": "理事長柯葉宜",
    "法人名稱": "社團法人苗栗縣自閉症協進會",
    "設立登記日期": "0960815",
    "主事務所": "苗栗縣竹南鎮大厝里20鄰環市路二段10號",
    "目的": "本會以協助身心障礙者，尤以自閉症為主，經由醫療、教育、復健、職訓、就業及安養等相關服務，得以增進其人際關係，促進正常語言發展，具備社會化生活能力為宗旨。",
    "捐助方法": "入會費、常年會費、永久會員會費、事業費、會員捐款、委託收益、基金及孳息、其他收入。",
    "許可機關日期": "苗栗縣政府96年6月25日府社政字第0960092403號函",
    "存立時期": "永久",
    "財產總額": "280685",
    "結案原因": "1",
    "結案日期": "1030221",
    "歸檔日期": "",
    "發證日期": "1030310",
    "送達代收人姓名": "",
    "送達代收人住址": "",
    "郵遞區號": "",
    "清算人": "",
    "變更原因": "法人主事務所變更，由苗栗縣竹南鎮康德街98巷18號變更為苗栗縣竹南鎮大厝里20鄰環市路二段10號。",
    "註銷日期": "",
    "撤銷日期": "",
    "撤(註)銷機關文號": "",
    "撤(註)銷原因 ": "",
    "url": {
        "staff": "http:\/\/cdcb.judicial.gov.tw\/abbs\/wkw\/WHD6K04.jsp?bc=103&cd=%AAk%B5n%A5L&de=000003&ef=MLD&fg=1",
        "office": "http:\/\/cdcb.judicial.gov.tw\/abbs\/wkw\/WHD6K07.jsp?bc=103&cd=%AAk%B5n%A5L&de=000003&ef=MLD&fg=1"
    },
    "董監事": [],
    "分事務所": []
}