{
    "登記案號": "105法登社000002",
    "類別": "2",
    "案由": "1",
    "主任": "陳雪芬",
    "登記號數": "543",
    "收件日期": "1050330",
    "登記日期": "1050420",
    "公告日期": "1050421",
    "登記簿": "18冊79頁",
    "任期判定": "",
    "屆期判定": "",
    "法人代表": "張正吉",
    "法人名稱": "社團法人中華台商青創交流協進會",
    "設立登記日期": "1050420",
    "主事務所": "嘉義市竹圍里友竹街71號",
    "目的": "倡導以人為本，重視心靈改革，透過專業訓練啟發本能智慧，結合青年企業經營人及知識份之，力求專業視野的態度檢視社會經濟，促進交流合作，協助解決企業經營與發展問題，提升青年就業與協助創業相輔相成機制，促進社會經濟繁榮。",
    "捐助方法": "會員會費等",
    "許可機關日期": "內政部105年1月26日台內團字第1050004215號函",
    "存立時期": "永久",
    "財產總額": "0",
    "結案原因": "1",
    "結案日期": "1050420",
    "歸檔日期": "",
    "發證日期": "",
    "送達代收人姓名": "",
    "送達代收人住址": "",
    "郵遞區號": "",
    "清算人": "",
    "變更原因": "",
    "註銷日期": "",
    "撤銷日期": "",
    "撤(註)銷機關文號": "",
    "撤(註)銷原因 ": "",
    "url": {
        "staff": "http:\/\/cdcb.judicial.gov.tw\/abbs\/wkw\/WHD6K04.jsp?bc=105&cd=%AAk%B5n%AA%C0&de=000002&ef=CYD&fg=1",
        "office": "http:\/\/cdcb.judicial.gov.tw\/abbs\/wkw\/WHD6K07.jsp?bc=105&cd=%AAk%B5n%AA%C0&de=000002&ef=CYD&fg=1"
    },
    "董監事": [
        [
            "理事長",
            "張正吉"
        ],
        [
            "常務理事",
            "王雅玲"
        ],
        [
            "常務理事",
            "陳國忠"
        ],
        [
            "理事",
            "黃金英"
        ],
        [
            "理事",
            "陳凱成"
        ],
        [
            "理事",
            "王亭妤"
        ],
        [
            "理事",
            "胡美惠"
        ],
        [
            "理事",
            "林靖容"
        ],
        [
            "理事",
            "李淑美"
        ],
        [
            "常務監事",
            "詹欣芸"
        ],
        [
            "監事",
            "黃美華"
        ]
    ],
    "分事務所": []
}